python_packaging_sc/__init__.py
python_packaging_sc/maths.py
python_packaging_sc-0.0.3.dist-info/LICENSE
python_packaging_sc-0.0.3.dist-info/METADATA
python_packaging_sc-0.0.3.dist-info/WHEEL
python_packaging_sc-0.0.3.dist-info/top_level.txt
python_packaging_sc-0.0.3.dist-info/RECORD
